argostranslategui/__init__.py
argostranslategui/gui.py
argostranslategui-1.6.5.data/scripts/argos-translate-gui
argostranslategui-1.6.5.dist-info/LICENSE
argostranslategui-1.6.5.dist-info/METADATA
argostranslategui-1.6.5.dist-info/WHEEL
argostranslategui-1.6.5.dist-info/top_level.txt
argostranslategui-1.6.5.dist-info/RECORD
