Metadata-Version: 2.1
Name: argostranslategui
Version: 1.6.5
Summary: Graphical user interface for Argos Translate
Home-page: https://www.argosopentech.com
Author: Argos Open Technologies, LLC
Author-email: admin@argosopentech.com
License: UNKNOWN
Platform: UNKNOWN
License-File: LICENSE
